odoo/addons/account_balance_line/README.rst
odoo/addons/account_balance_line/__init__.py
odoo/addons/account_balance_line/__manifest__.py
odoo/addons/account_balance_line/i18n/account_balance_line.pot
odoo/addons/account_balance_line/i18n/ar.po
odoo/addons/account_balance_line/i18n/bs.po
odoo/addons/account_balance_line/i18n/ca.po
odoo/addons/account_balance_line/i18n/cs.po
odoo/addons/account_balance_line/i18n/de.po
odoo/addons/account_balance_line/i18n/en_GB.po
odoo/addons/account_balance_line/i18n/es.po
odoo/addons/account_balance_line/i18n/es_CR.po
odoo/addons/account_balance_line/i18n/es_EC.po
odoo/addons/account_balance_line/i18n/es_MX.po
odoo/addons/account_balance_line/i18n/fr.po
odoo/addons/account_balance_line/i18n/gl.po
odoo/addons/account_balance_line/i18n/hr.po
odoo/addons/account_balance_line/i18n/hr_HR.po
odoo/addons/account_balance_line/i18n/hu.po
odoo/addons/account_balance_line/i18n/it.po
odoo/addons/account_balance_line/i18n/ja.po
odoo/addons/account_balance_line/i18n/lt.po
odoo/addons/account_balance_line/i18n/mk.po
odoo/addons/account_balance_line/i18n/mn.po
odoo/addons/account_balance_line/i18n/nb.po
odoo/addons/account_balance_line/i18n/nb_NO.po
odoo/addons/account_balance_line/i18n/nl.po
odoo/addons/account_balance_line/i18n/nl_BE.po
odoo/addons/account_balance_line/i18n/pt.po
odoo/addons/account_balance_line/i18n/pt_BR.po
odoo/addons/account_balance_line/i18n/pt_PT.po
odoo/addons/account_balance_line/i18n/ro.po
odoo/addons/account_balance_line/i18n/ru.po
odoo/addons/account_balance_line/i18n/sl.po
odoo/addons/account_balance_line/i18n/sv.po
odoo/addons/account_balance_line/i18n/tr.po
odoo/addons/account_balance_line/i18n/zh_CN.po
odoo/addons/account_balance_line/i18n/zh_TW.po
odoo/addons/account_balance_line/readme/CONTRIBUTORS.rst
odoo/addons/account_balance_line/readme/DESCRIPTION.rst
odoo/addons/account_balance_line/readme/USAGE.rst
odoo/addons/account_balance_line/static/description/icon.png
odoo13_addon_account_balance_line-13.0.1.0.1.dev5.dist-info/METADATA
odoo13_addon_account_balance_line-13.0.1.0.1.dev5.dist-info/WHEEL
odoo13_addon_account_balance_line-13.0.1.0.1.dev5.dist-info/top_level.txt
odoo13_addon_account_balance_line-13.0.1.0.1.dev5.dist-info/RECORD
